AUTHORS.rst
CONTRIBUTING.rst
HISTORY.rst
LICENSE
MANIFEST.in
README.rst
setup.cfg
setup.py
docs/Makefile
docs/authors.rst
docs/conf.py
docs/contributing.rst
docs/history.rst
docs/index.rst
docs/installation.rst
docs/make.bat
docs/readme.rst
docs/usage.rst
docs/_static/ner_input.png
docs/_static/ner_output.png
fst2/__init__.py
fst2/commons.py
fst2/main.py
fst2/pipelines.py
fst2/processers.py
fst2/utils.py
fst2.egg-info/PKG-INFO
fst2.egg-info/SOURCES.txt
fst2.egg-info/dependency_links.txt
fst2.egg-info/entry_points.txt
fst2.egg-info/not-zip-safe
fst2.egg-info/requires.txt
fst2.egg-info/top_level.txt
fst2/default_configs/__init__.py
fst2/default_configs/configs.py
fst2/default_configs/temp.py
tests/__init__.py
tests/test_fst2.py