Metadata-Version: 1.2
Name: fst2
Version: 0.1.4
Summary: train nlp models much more easily
Home-page: https://github.com/superjcd/fst2
Author: Jiang Chaodi
Author-email: 929760274@qq.com
License: MIT license
Keywords: fst2
Platform: UNKNOWN
Classifier: Development Status :: 2 - Pre-Alpha
Classifier: Intended Audience :: Developers
Classifier: License :: OSI Approved :: MIT License
Classifier: Natural Language :: English
Classifier: Programming Language :: Python :: 3
Classifier: Programming Language :: Python :: 3.5
Classifier: Programming Language :: Python :: 3.6
Classifier: Programming Language :: Python :: 3.7
Classifier: Programming Language :: Python :: 3.8
Requires-Python: >=3.5
